CHANGELOG.txt
LICENSE.txt
MANIFEST.in
README.txt
ez_setup.py
setup.cfg
setup.py
WarningPipe.egg-info/PKG-INFO
WarningPipe.egg-info/SOURCES.txt
WarningPipe.egg-info/dependency_links.txt
WarningPipe.egg-info/entry_points.txt
WarningPipe.egg-info/not-zip-safe
WarningPipe.egg-info/requires.txt
WarningPipe.egg-info/top_level.txt
doc/Makefile
doc/index.txt
doc/source/api.rst
doc/source/conf.py
doc/source/index.rst
doc/source/manual.rst
example/README.txt
test/README.txt
test/doc.py
warningpipe/__init__.py