Metadata-Version: 1.0
Name: WarningPipe
Version: 0.1.0
Summary: A pipe to allow warning messages to be logged to a database and displayed as a flash message in the browser without raising an exception
Home-page: http://jimmyg.org/work/code/warningpipe/index.html
Author: James Gardner
Author-email: james@<package hompage domain>
License: GNU AGPLv3
Platform: UNKNOWN
Classifier: Development Status :: 3 - Alpha
Classifier: License :: OSI Approved :: GNU Affero General Public License v3
Classifier: Programming Language :: Python
